{
  "suggest.noselect": true,
  "suggest.preferCompleteThanJumpPlaceholder": true,
  "diagnostic.refreshOnInsertMode": true,
  "python.sortImports.path": "isort",
  "python.linting.pylamaEnabled": true,
  "python.linting.pylamaPath": "pylama",
  "python.linting.pylamaArgs": ["--options=/Users/hiroki_sawano/pylama.ini"],
  "python.formatting.provider": "autopep8",
  "python.formatting.autopep8Path": "/Users/hiroki_sawano/miniconda3/bin/autopep8",
  "pyright.organizeimports.provider": "isort",
  "eslint.enable": true,
  "tsserver.enableJavascript": true,
  "typescript.format.insertSpaceAfterOpeningAndBeforeClosingNonemptyBraces": true,
  "java.home": "/Library/Java/JavaVirtualMachines/adoptopenjdk-14.jdk/Contents/Home/",
  "java.configuration.runtimes": [
    {
      "name": "JavaSE-1.8",
      "path": "/Library/Java/JavaVirtualMachines/jdk1.8.0_191.jdk/Contents/Home/",
      "default": true
    }
  ],
  "java.referencesCodeLens.enabled": true,
  "java.import.maven.enabled": true,
  "java.autobuild.enabled": true,
  "java.format.enabled": true,
  "java.format.settings.url": "/Users/hiroki_sawano/formatter.xml",
  "java.format.comments.enabled": true,
  "java.format.onType.enabled": true,
  "java.signatureHelp.enabled": true,
  "java.completion.importOrder": ["java", "javax", "org", "com"],
  "yaml.format.enable": true,
  "yaml.validate": true,
  "yaml.schemas": {},
  "yaml.customTags": [
    "!And",
    "!And sequence",
    "!If",
    "!If sequence",
    "!Not",
    "!Not sequence",
    "!Equals",
    "!Equals sequence",
    "!Or",
    "!Or sequence",
    "!FindInMap",
    "!FindInMap sequence",
    "!Base64",
    "!Join",
    "!Join sequence",
    "!Cidr",
    "!Ref",
    "!Sub",
    "!Sub sequence",
    "!GetAtt",
    "!GetAZs",
    "!ImportValue",
    "!ImportValue sequence",
    "!Select",
    "!Select sequence",
    "!Split",
    "!Split sequence"
  ],
  "yaml.completion": true
}
